main.py
full_context-0.0.1.dist-info/METADATA
full_context-0.0.1.dist-info/WHEEL
full_context-0.0.1.dist-info/top_level.txt
full_context-0.0.1.dist-info/RECORD
