Metadata-Version: 2.4
Name: full-context
Version: 0.0.1
Summary: Full context provide a single layer of abstraction to work with all the data sources for agents.
Author-email: ra1han <hello@pl.com>
Project-URL: Homepage, https://github.com/imum-ai/promptlab
Project-URL: Issues, https://github.com/imum-ai/promptlab/issues
Classifier: Programming Language :: Python :: 3
Classifier: License :: OSI Approved :: MIT License
Classifier: Operating System :: OS Independent
Requires-Python: >=3.8
